micecraft/MiceCraftDemo.py
micecraft/__init__.py
micecraft/devices/__init__.py
micecraft/devices/antenna_rfid/AntennaRFID.py
micecraft/devices/antenna_rfid/__init__.py
micecraft/devices/fed3/Fed3.py
micecraft/devices/fed3/__init__.py
micecraft/devices/fed3/arduino/fed3 code upload help.txt
micecraft/devices/fed3/arduino/fed/fedControl/fedControl.ino
micecraft/devices/gate/Door.py
micecraft/devices/gate/Gate.py
micecraft/devices/gate/Parameters.py
micecraft/devices/gate/__init__.py
micecraft/devices/gate/arduino_reader/ArduinoReader.py
micecraft/devices/gate/arduino_reader/__init__.py
micecraft/devices/gate/arduino_reader/arduino/balance/balance.ino
micecraft/devices/gate/dxl_control/Ax12Motor.py
micecraft/devices/gate/dxl_control/MotorManager.py
micecraft/devices/gate/dxl_control/__init__.py
micecraft/devices/gate/dxl_control/ax12_control_table.py
micecraft/devices/lever/Lever.py
micecraft/devices/lever/__init__.py
micecraft/devices/lever/arduino/leverControl/leverControl.ino
micecraft/examples/Exp1_Fed.py
micecraft/examples/Exp2_Gate.py
micecraft/examples/GateExample.py
micecraft/examples/GateInGui.py
micecraft/examples/LeverInGui.py
micecraft/examples/LeverTest.py
micecraft/examples/LiveMouseTrackerEvent.py
micecraft/examples/Report0001passs.py
micecraft/examples/__init__.py
micecraft/examples/cameraRecordDemo.py
micecraft/examples/html_output/index.html
micecraft/examples/html_output/scripts.js
micecraft/examples/html_output/styles.css
micecraft/soft/__init__.py
micecraft/soft/alarm/Alarm.py
micecraft/soft/alarm/__init__.py
micecraft/soft/camera_recorder/CameraRecorder.py
micecraft/soft/camera_recorder/__init__.py
micecraft/soft/com_manager/ComManager.py
micecraft/soft/com_manager/__init__.py
micecraft/soft/device_event/DeviceEvent.py
micecraft/soft/device_event/__init__.py
micecraft/soft/gui/LMTVisualExperimentCore.py
micecraft/soft/gui/VisualDeviceAlarmStatus.py
micecraft/soft/gui/VisualStorageAlarm.py
micecraft/soft/gui/WBlock.py
micecraft/soft/gui/WFed.py
micecraft-0.0.9.dist-info/LICENSE
micecraft-0.0.9.dist-info/METADATA
micecraft-0.0.9.dist-info/WHEEL
micecraft-0.0.9.dist-info/top_level.txt
micecraft-0.0.9.dist-info/RECORD
