Metadata-Version: 2.1
Name: micecraft
Version: 0.0.9
Summary: MiceCraft
Author-email: Fabrice de Chaumont <fabrice.de.chaumont@gmail.com>
Project-URL: Homepage, https://github.com/micecraft
Project-URL: Issues, https://github.com/micecraft/issues
Project-URL: documentation, https://micecraft.org
Classifier: Programming Language :: Python :: 3
Classifier: Operating System :: OS Independent
Requires-Python: >=3.8
License-File: LICENSE
Requires-Dist: numpy
Requires-Dist: pyserial
Requires-Dist: dynamixel-sdk
Requires-Dist: pyqt6
Requires-Dist: matplotlib
Requires-Dist: opencv-python
Requires-Dist: jinja2
Requires-Dist: plotly
Requires-Dist: xlsxwriter
